{
    "jobs": [
        {
            "title": "Student Wellness Support Specialist",
            "school": "Athabasca University",
            "date": "2024-06-26",
            "link": "https://athabascau.acquiretm.com/job_details_clean.aspx?id=2720"
        },
        {
            "title": "Individualized Study Tutor - INST 203",
            "school": "Athabasca University",
            "date": "2024-06-26",
            "link": "https://athabascau.acquiretm.com/job_details_clean.aspx?id=2763"
        },
        {
            "title": "Individualized Study Tutor - ENGL 351, 361,458",
            "school": "Athabasca University",
            "date": "2024-06-26",
            "link": "https://athabascau.acquiretm.com/job_details_clean.aspx?id=2791"
        },
        {
            "title": "Individualized Study Tutor - NURS 350",
            "school": "Athabasca University",
            "date": "2024-06-26",
            "link": "https://athabascau.acquiretm.com/job_details_clean.aspx?id=2807"
        },
        {
            "title": "Data Acquisition and Analysis Technician",
            "school": "Athabasca University",
            "date": "2024-06-26",
            "link": "https://athabascau.acquiretm.com/job_details_clean.aspx?id=2783"
        },
        {
            "title": "Intermediate Academic Records Administrator",
            "school": "Athabasca University",
            "date": "2024-06-26",
            "link": "https://athabascau.acquiretm.com/job_details_clean.aspx?id=2775"
        },
        {
            "title": "Academic Expert - COMP 210",
            "school": "Athabasca University",
            "date": "2024-06-26",
            "link": "https://athabascau.acquiretm.com/job_details_clean.aspx?id=2798"
        },
        {
            "title": "Academic Expert/Marker - ORGB 364",
            "school": "Athabasca University",
            "date": "2024-06-26",
            "link": "https://athabascau.acquiretm.com/job_details_clean.aspx?id=2806"
        },
        {
            "title": "Assistant Coordinator, Enrolment Services and Academic Records",
            "school": "Athabasca University",
            "date": "2024-06-26",
            "link": "https://athabascau.acquiretm.com/job_details_clean.aspx?id=2766"
        },
        {
            "title": "Collections Services Librarian",
            "school": "Athabasca University",
            "date": "2024-06-26",
            "link": "https://athabascau.acquiretm.com/job_details_clean.aspx?id=2754"
        },
        {
            "title": "Associate Vice President, Indigenous Conciliation (Virtual with Place-Based Functions)",
            "school": "Athabasca University",
            "date": "2024-06-26",
            "link": "https://athabascau.acquiretm.com/job_details_clean.aspx?id=2774"
        },
        {
            "title": "Student Advisor",
            "school": "Athabasca University",
            "date": "2024-06-26",
            "link": "https://athabascau.acquiretm.com/job_details_clean.aspx?id=2777"
        },
        {
            "title": "Intermediate Articulation Assistant (Virtual - Alberta)",
            "school": "Athabasca University",
            "date": "2024-06-26",
            "link": "https://athabascau.acquiretm.com/job_details_clean.aspx?id=2694"
        },
        {
            "title": "Cloud Systems Administrator: Architecture (Virtual)",
            "school": "Athabasca University",
            "date": "2024-06-26",
            "link": "https://athabascau.acquiretm.com/job_details_clean.aspx?id=2761"
        },
        {
            "title": "Tier 2 Canada Research Chair - Emerging Technologies For Digital Learning and Open Education",
            "school": "Athabasca University",
            "date": "2024-06-26",
            "link": "https://athabascau.acquiretm.com/job_details_clean.aspx?id=2782"
        },
        {
            "title": "Casual Administrative Support Positions - Other Locations",
            "school": "Athabasca University",
            "date": "2024-06-26",
            "link": "https://athabascau.acquiretm.com/job_details_clean.aspx?id=2769"
        },
        {
            "title": "Casual Administrative Support Positions - Athabasca, AB",
            "school": "Athabasca University",
            "date": "2024-06-26",
            "link": "https://athabascau.acquiretm.com/job_details_clean.aspx?id=2771"
        },
        {
            "title": "Academic Expert - Indigenous Law",
            "school": "Athabasca University",
            "date": "2024-06-26",
            "link": "https://athabascau.acquiretm.com/job_details_clean.aspx?id=2665"
        },
        {
            "title": "Records Evaluator",
            "school": "Mount Royal University",
            "date": "2024-06-26",
            "link": "https://mtroyalca.hua.hrsmart.com/hr/ats/Posting/view/2815"
        },
        {
            "title": "Inventory Coordinator",
            "school": "Mount Royal University",
            "date": "2024-06-26",
            "link": "https://mtroyalca.hua.hrsmart.com/hr/ats/Posting/view/2814"
        },
        {
            "title": "Inventory Control Supervisor",
            "school": "Mount Royal University",
            "date": "2024-06-26",
            "link": "https://mtroyalca.hua.hrsmart.com/hr/ats/Posting/view/2817"
        },
        {
            "title": "Credit Contract Appointment, General Education",
            "school": "Mount Royal University",
            "date": "2024-06-26",
            "link": "https://mtroyalca.hua.hrsmart.com/hr/ats/Posting/view/2812"
        },
        {
            "title": "Assistant Chief Flight Instructor",
            "school": "Mount Royal University",
            "date": "2024-06-26",
            "link": "https://mtroyalca.hua.hrsmart.com/hr/ats/Posting/view/2810"
        },
        {
            "title": "Public Services Assistant, Scholarship and Open Publishing",
            "school": "Mount Royal University",
            "date": "2024-06-26",
            "link": "https://mtroyalca.hua.hrsmart.com/hr/ats/Posting/view/2805"
        },
        {
            "title": "Public Services Assistant, Maker Studio",
            "school": "Mount Royal University",
            "date": "2024-06-26",
            "link": "https://mtroyalca.hua.hrsmart.com/hr/ats/Posting/view/2806"
        },
        {
            "title": "Information Design: Past, Present, and Future - Credit Contract Appointment",
            "school": "Mount Royal University",
            "date": "2024-06-26",
            "link": "https://mtroyalca.hua.hrsmart.com/hr/ats/Posting/view/2801"
        },
        {
            "title": "Credit Contract Appointment, General Education",
            "school": "Mount Royal University",
            "date": "2024-06-26",
            "link": "https://mtroyalca.hua.hrsmart.com/hr/ats/Posting/view/2790"
        },
        {
            "title": "Credit Contract Appointment, Computing",
            "school": "Mount Royal University",
            "date": "2024-06-26",
            "link": "https://mtroyalca.hua.hrsmart.com/hr/ats/Posting/view/2795"
        },
        {
            "title": "Senior Lecturer of Finance (Limited-Term)",
            "school": "Mount Royal University",
            "date": "2024-06-26",
            "link": "https://mtroyalca.hua.hrsmart.com/hr/ats/Posting/view/2793"
        },
        {
            "title": "Senior Lecturer, General Management",
            "school": "Mount Royal University",
            "date": "2024-06-26",
            "link": "https://mtroyalca.hua.hrsmart.com/hr/ats/Posting/view/2789"
        },
        {
            "title": "Assistant Professor, School of Nursing and Midwifery (Limited Term)",
            "school": "Mount Royal University",
            "date": "2024-06-26",
            "link": "https://mtroyalca.hua.hrsmart.com/hr/ats/Posting/view/2754"
        },
        {
            "title": "Assistant Professor, School of Nursing & Midwifery",
            "school": "Mount Royal University",
            "date": "2024-06-26",
            "link": "https://mtroyalca.hua.hrsmart.com/hr/ats/Posting/view/2752"
        },
        {
            "title": "Credit Contract Appointments, Entrepreneurship, Marketing and Social Innovation",
            "school": "Mount Royal University",
            "date": "2024-06-26",
            "link": "https://mtroyalca.hua.hrsmart.com/hr/ats/Posting/view/2736"
        },
        {
            "title": "Counsellor",
            "school": "Mount Royal University",
            "date": "2024-06-26",
            "link": "https://mtroyalca.hua.hrsmart.com/hr/ats/Posting/view/2672"
        },
        {
            "title": "Thinking with Type - Credit Contract Appointment",
            "school": "Mount Royal University",
            "date": "2024-06-26",
            "link": "https://mtroyalca.hua.hrsmart.com/hr/ats/Posting/view/2710"
        },
        {
            "title": "Admissions and Recruitment Specialist, Indigenous",
            "school": "Mount Royal University",
            "date": "2024-06-26",
            "link": "https://mtroyalca.hua.hrsmart.com/hr/ats/Posting/view/2697"
        },
        {
            "title": "Assistant Professor, Finance",
            "school": "Mount Royal University",
            "date": "2024-06-26",
            "link": "https://mtroyalca.hua.hrsmart.com/hr/ats/Posting/view/2676"
        },
        {
            "title": "Daytime / Event Box Office",
            "school": "Mount Royal University",
            "date": "2024-06-26",
            "link": "https://mtroyalca.hua.hrsmart.com/hr/ats/Posting/view/2668"
        },
        {
            "title": "Ralph Klein Chair in Communication Studies",
            "school": "Mount Royal University",
            "date": "2024-06-26",
            "link": "https://mtroyalca.hua.hrsmart.com/hr/ats/Posting/view/2654"
        },
        {
            "title": "Senior Social Media Strategist",
            "school": "Mount Royal University",
            "date": "2024-06-26",
            "link": "https://mtroyalca.hua.hrsmart.com/hr/ats/Posting/view/2455"
        },
        {
            "title": "Assistant Professor, Creative Writing",
            "school": "Mount Royal University",
            "date": "2024-06-26",
            "link": "https://mtroyalca.hua.hrsmart.com/hr/ats/Posting/view/2649"
        },
        {
            "title": "Assistant Professor, Indigenous Science",
            "school": "Mount Royal University",
            "date": "2024-06-26",
            "link": "https://mtroyalca.hua.hrsmart.com/hr/ats/Posting/view/2642"
        },
        {
            "title": "Assistant Professor, Tenure-Track in Business and Communications",
            "school": "Mount Royal University",
            "date": "2024-06-26",
            "link": "https://mtroyalca.hua.hrsmart.com/hr/ats/Posting/view/2643"
        },
        {
            "title": "COMMUNICATIONS ADVISOR (BAND LEVEL 7)",
            "school": "Memorial University",
            "date": "2024-06-26",
            "link": "https://www.mun.ca/hr/careers/employment-opportunity/?id=5370"
        },
        {
            "title": "ACCOUNTING CLERK (BAND LEVEL 4)",
            "school": "Memorial University",
            "date": "2024-06-26",
            "link": "https://www.mun.ca/hr/careers/employment-opportunity/?id=5372"
        },
        {
            "title": "ACADEMIC PROGRAM ASSISTANT (BAND LEVEL 6)",
            "school": "Memorial University",
            "date": "2024-06-26",
            "link": "https://www.mun.ca/hr/careers/employment-opportunity/?id=5362"
        },
        {
            "title": "ASSOCIATE COUNSEL (BAND LEVEL 12)",
            "school": "Memorial University",
            "date": "2024-06-26",
            "link": "https://www.mun.ca/hr/careers/employment-opportunity/?id=5360"
        },
        {
            "title": "RECRUITMENT CONSULTANT (BAND LEVEL 8)",
            "school": "Memorial University",
            "date": "2024-06-26",
            "link": "https://www.mun.ca/hr/careers/employment-opportunity/?id=5358"
        },
        {
            "title": "DEVELOPMENT OFFICER (BAND 8)",
            "school": "Memorial University",
            "date": "2024-06-26",
            "link": "https://www.mun.ca/hr/careers/employment-opportunity/?id=5353"
        },
        {
            "title": "NURSING LABORATORY INSTRUCTOR (BAND LEVEL 10)",
            "school": "Memorial University",
            "date": "2024-06-26",
            "link": "https://www.mun.ca/hr/careers/employment-opportunity/?id=5337"
        },
        {
            "title": "INTERMEDIATE SECRETARY (BAND LEVEL 4)",
            "school": "Memorial University",
            "date": "2024-06-26",
            "link": "https://www.mun.ca/hr/careers/employment-opportunity/?id=5339"
        },
        {
            "title": "ENGINEERING TECHNOLOGIST III (BAND LEVEL 7)",
            "school": "Memorial University",
            "date": "2024-06-26",
            "link": "https://www.mun.ca/hr/careers/employment-opportunity/?id=5341"
        },
        {
            "title": "ACCOUNTING CLERK (BAND LEVEL 4)",
            "school": "Memorial University",
            "date": "2024-06-26",
            "link": "https://www.mun.ca/hr/careers/employment-opportunity/?id=5343"
        },
        {
            "title": "ADMINISTRATIVE STAFF SPECIALIST II (BAND LEVEL 7)",
            "school": "Memorial University",
            "date": "2024-06-26",
            "link": "https://www.mun.ca/hr/careers/employment-opportunity/?id=5334"
        },
        {
            "title": "ADMINISTRATIVE SUPPORT CANDIDATE LIST FOR SHORT-TERM CONTRACTS AND TEMPORARY POSITIONS",
            "school": "Memorial University",
            "date": "2024-06-26",
            "link": "https://www.mun.ca/hr/careers/employment-opportunity/?id=5222"
        },
        {
            "title": "MANAGER, ELECTRICAL SYSTEMS",
            "school": "Memorial University",
            "date": "2024-06-26",
            "link": "https://www.mun.ca/hr/careers/employment-opportunity/?id=4595"
        },
        {
            "title": "CLERK III (BAND LEVEL 4)",
            "school": "Memorial University",
            "date": "2024-06-26",
            "link": "https://www.mun.ca/hr/careers/employment-opportunity/?id=5346"
        },
        {
            "title": "PROCUREMENT AND COMPLIANCE OFFICER (BAND LEVEL 6)",
            "school": "Memorial University",
            "date": "2024-06-26",
            "link": "https://www.mun.ca/hr/careers/employment-opportunity/?id=5348"
        },
        {
            "title": "INSTRUCTORS",
            "school": "Memorial University",
            "date": "2024-06-26",
            "link": "https://www.mun.ca/hr/careers/employment-opportunity/?id=4940"
        },
        {
            "title": "Research & Technical Personnel (RTP)",
            "school": "Memorial University",
            "date": "2024-06-26",
            "link": "https://www.mun.ca/hr/careers/employment-opportunity/?id=4941"
        },
        {
            "title": "INSTRUCTOR SCHOOL OF FISHERIES \u2013 ELIGIBILITY LIST",
            "school": "Memorial University",
            "date": "2024-06-26",
            "link": "https://www.mun.ca/hr/careers/employment-opportunity/?id=3031"
        },
        {
            "title": "Instructors",
            "school": "Memorial University",
            "date": "2024-06-26",
            "link": "https://www.mun.ca/hr/careers/employment-opportunity/?id=1395"
        },
        {
            "title": "NURSING LABORATORY INSTRUCTOR (BAND LEVEL 10)",
            "school": "Memorial University",
            "date": "2024-06-26",
            "link": "https://www.mun.ca/hr/careers/employment-opportunity/?id=5332"
        },
        {
            "title": "SCIENCE TECHNICIAN III (BAND LEVEL 5)",
            "school": "Memorial University",
            "date": "2024-06-26",
            "link": "https://www.mun.ca/hr/careers/employment-opportunity/?id=5350"
        },
        {
            "title": "STAGE MANAGER (BAND LEVEL 8)",
            "school": "Memorial University",
            "date": "2024-06-26",
            "link": "https://www.mun.ca/hr/careers/employment-opportunity/?id=5330"
        },
        {
            "title": "LABORATORY INSTRUCTOR",
            "school": "Memorial University",
            "date": "2024-06-26",
            "link": "https://www.mun.ca/hr/careers/employment-opportunity/?id=2003"
        },
        {
            "title": "Interlibrary Loan Technician - Library",
            "school": "MacEwan University",
            "date": "No Date Provided",
            "link": "https://www.macewan.ca/about-macewan/careers/opportunities/postings/?competition=24.06.193"
        },
        {
            "title": "Retail Sales Associate (Casual) - Bookstore, Campus Services",
            "school": "MacEwan University",
            "date": "No Date Provided",
            "link": "https://www.macewan.ca/about-macewan/careers/opportunities/postings/?competition=24.06.192"
        },
        {
            "title": "Executive Assistant to the Provost - Office of the Provost and Vice-President, Academic",
            "school": "MacEwan University",
            "date": "No Date Provided",
            "link": "https://www.macewan.ca/about-macewan/careers/opportunities/postings/?competition=24.06.189"
        },
        {
            "title": "IT Senior Security Analyst - Information Technology Services",
            "school": "MacEwan University",
            "date": "No Date Provided",
            "link": "https://www.macewan.ca/about-macewan/careers/opportunities/postings/?competition=24.06.188"
        },
        {
            "title": "Front Desk Associate - kih\u00eaw waciston Indigenous Centre",
            "school": "MacEwan University",
            "date": "No Date Provided",
            "link": "https://www.macewan.ca/about-macewan/careers/opportunities/postings/?competition=24.06.187"
        },
        {
            "title": "Residence Life Coordinator (2 Positions) - Residence Life",
            "school": "MacEwan University",
            "date": "No Date Provided",
            "link": "https://www.macewan.ca/about-macewan/careers/opportunities/postings/?competition=24.06.186"
        },
        {
            "title": "Sessional Instructor, Math - University Preparation, School of Continuing Education",
            "school": "MacEwan University",
            "date": "No Date Provided",
            "link": "https://www.macewan.ca/about-macewan/careers/opportunities/postings/?competition=24.06.185"
        },
        {
            "title": "Program Assistant - School of Continuing Education",
            "school": "MacEwan University",
            "date": "No Date Provided",
            "link": "https://www.macewan.ca/about-macewan/careers/opportunities/postings/?competition=24.06.183"
        },
        {
            "title": "Manager - Exam Services, Student Affairs",
            "school": "MacEwan University",
            "date": "No Date Provided",
            "link": "https://www.macewan.ca/about-macewan/careers/opportunities/postings/?competition=24.06.181"
        },
        {
            "title": "HSE Specialist \u2013 Campus Services - Campus Services",
            "school": "MacEwan University",
            "date": "No Date Provided",
            "link": "https://www.macewan.ca/about-macewan/careers/opportunities/postings/?competition=24.06.175"
        },
        {
            "title": "Recreation Consultant - Sports and Wellness",
            "school": "MacEwan University",
            "date": "No Date Provided",
            "link": "https://www.macewan.ca/about-macewan/careers/opportunities/postings/?competition=24.06.174"
        },
        {
            "title": "Counsellor I - Wellness and Psychological Services, Student Affairs",
            "school": "MacEwan University",
            "date": "No Date Provided",
            "link": "https://www.macewan.ca/about-macewan/careers/opportunities/postings/?competition=24.05.167"
        },
        {
            "title": "Accounting Tech II (15 Month Term) - Financial Services",
            "school": "MacEwan University",
            "date": "No Date Provided",
            "link": "https://www.macewan.ca/about-macewan/careers/opportunities/postings/?competition=24.05.164"
        },
        {
            "title": "Sessional Instructor, Design - Faculty of Fine Arts and Communications",
            "school": "MacEwan University",
            "date": "No Date Provided",
            "link": "https://www.macewan.ca/about-macewan/careers/opportunities/postings/?competition=24.05.158"
        },
        {
            "title": "Assistant Professor, Spanish - Department of Humanities, Faculty of Arts and Science",
            "school": "MacEwan University",
            "date": "No Date Provided",
            "link": "https://www.macewan.ca/about-macewan/careers/opportunities/postings/?competition=24.05.149"
        },
        {
            "title": "Sessional Instructor - Department of Computer Science, Faculty of Arts and Science",
            "school": "MacEwan University",
            "date": "No Date Provided",
            "link": "https://www.macewan.ca/about-macewan/careers/opportunities/postings/?competition=24.05.148"
        },
        {
            "title": "Sessional Instructor, Gerontology & Hospice Palliative Care - Professional Health Education, School of Continuing Education",
            "school": "MacEwan University",
            "date": "No Date Provided",
            "link": "https://www.macewan.ca/about-macewan/careers/opportunities/postings/?competition=24.05.142"
        },
        {
            "title": "Assistant Professor, Piano (Internal Only - Teaching and Service) - Department of Music, Faculty of Fine Arts and Communications",
            "school": "MacEwan University",
            "date": "No Date Provided",
            "link": "https://www.macewan.ca/about-macewan/careers/opportunities/postings/?competition=24.04.125"
        },
        {
            "title": "Nurse Educators - Bachelor of Science in Nursing & Psychiatric Nursing Programs, Faculty of Nursing",
            "school": "MacEwan University",
            "date": "No Date Provided",
            "link": "https://www.macewan.ca/about-macewan/careers/opportunities/postings/?competition=24.03.67"
        },
        {
            "title": "Assistant or Associate Professor (with initial appointment as Research Chair in International Health) - Department of Nursing Foundations, Faculty of Nursing",
            "school": "MacEwan University",
            "date": "No Date Provided",
            "link": "https://www.macewan.ca/about-macewan/careers/opportunities/postings/?competition=24.02.36"
        },
        {
            "title": "Assistant Professor, Psychiatric Nursing Programs - Department of Human Health and Science, Faculty of Nursing",
            "school": "MacEwan University",
            "date": "No Date Provided",
            "link": "https://www.macewan.ca/about-macewan/careers/opportunities/postings/?competition=23.11.360"
        },
        {
            "title": "Sessional Clinical Instructors - Faculty of Nursing",
            "school": "MacEwan University",
            "date": "No Date Provided",
            "link": "https://www.macewan.ca/about-macewan/careers/opportunities/postings/?competition=23.11.356"
        },
        {
            "title": "Sessional Instructor, Travel and Tourism - International Business, Marketing, Strategy, and Law, School of Business",
            "school": "MacEwan University",
            "date": "No Date Provided",
            "link": "https://www.macewan.ca/about-macewan/careers/opportunities/postings/?competition=23.10.271"
        },
        {
            "title": "Sessional Instructors - Psychology - Edmonton AB",
            "school": "Concordia University of Edmonton",
            "date": "No Date Provided",
            "link": "https://concordiaedmonton.startdate.ca/#/career/info/public/109?language=en"
        },
        {
            "title": "Assistant Professor, Information Technology - Edmonton AB",
            "school": "Concordia University of Edmonton",
            "date": "No Date Provided",
            "link": "https://concordiaedmonton.startdate.ca/#/career/info/public/84?language=en"
        },
        {
            "title": "Associate Professor, Clinical Psychology - Edmonton AB",
            "school": "Concordia University of Edmonton",
            "date": "No Date Provided",
            "link": "https://concordiaedmonton.startdate.ca/#/career/info/public/98?language=en"
        },
        {
            "title": "Administrative Assistant, Campus Life Programs (10 Month Term) - Edmonton AB",
            "school": "Concordia University of Edmonton",
            "date": "No Date Provided",
            "link": "https://concordiaedmonton.startdate.ca/#/career/info/public/129?language=en"
        },
        {
            "title": "Assistant Professor - Information Systems Assurance Management (ISAM) - Edmonton AB",
            "school": "Concordia University of Edmonton",
            "date": "No Date Provided",
            "link": "https://concordiaedmonton.startdate.ca/#/career/info/public/87?language=en"
        },
        {
            "title": "Assistant Professor, Environmental Health - Edmonton AB",
            "school": "Concordia University of Edmonton",
            "date": "No Date Provided",
            "link": "https://concordiaedmonton.startdate.ca/#/career/info/public/111?language=en"
        },
        {
            "title": "Administrative Assistant - Dean, Faculty of Science and Dean, Graduate Studies - Edmonton AB",
            "school": "Concordia University of Edmonton",
            "date": "No Date Provided",
            "link": "https://concordiaedmonton.startdate.ca/#/career/info/public/112?language=en"
        },
        {
            "title": "Career Planning Advisor - Edmonton AB",
            "school": "Concordia University of Edmonton",
            "date": "No Date Provided",
            "link": "https://concordiaedmonton.startdate.ca/#/career/info/public/123?language=en"
        },
        {
            "title": "Student Help - International Office - Edmonton AB",
            "school": "Concordia University of Edmonton",
            "date": "No Date Provided",
            "link": "https://concordiaedmonton.startdate.ca/#/career/info/public/122?language=en"
        },
        {
            "title": "Women's Basketball Head Coach - Edmonton AB",
            "school": "Concordia University of Edmonton",
            "date": "No Date Provided",
            "link": "https://concordiaedmonton.startdate.ca/#/career/info/public/124?language=en"
        },
        {
            "title": "Accounts Payable Coordinator - Edmonton AB",
            "school": "Concordia University of Edmonton",
            "date": "No Date Provided",
            "link": "https://concordiaedmonton.startdate.ca/#/career/info/public/125?language=en"
        },
        {
            "title": "Student Marketing Assistant - Edmonton AB",
            "school": "Concordia University of Edmonton",
            "date": "No Date Provided",
            "link": "https://concordiaedmonton.startdate.ca/#/career/info/public/108?language=en"
        },
        {
            "title": "Senior Grants and Contracts Officer - Edmonton AB",
            "school": "Concordia University of Edmonton",
            "date": "No Date Provided",
            "link": "https://concordiaedmonton.startdate.ca/#/career/info/public/126?language=en"
        },
        {
            "title": "Research Administration Coordinator - Edmonton AB",
            "school": "Concordia University of Edmonton",
            "date": "No Date Provided",
            "link": "https://concordiaedmonton.startdate.ca/#/career/info/public/127?language=en"
        },
        {
            "title": "Maintenance Generalist - Edmonton AB",
            "school": "Concordia University of Edmonton",
            "date": "No Date Provided",
            "link": "https://concordiaedmonton.startdate.ca/#/career/info/public/128?language=en"
        }
    ],
    "last_updated": "2024-06-26T00:01:12.402539"
}